ftw/referencewidget/__init__.py
ftw/referencewidget/behaviors.py
ftw/referencewidget/configure.zcml
ftw/referencewidget/converter.py
ftw/referencewidget/datagridfield.py
ftw/referencewidget/interfaces.py
ftw/referencewidget/overrides.zcml
ftw/referencewidget/referencewidget_handler.py
ftw/referencewidget/selectable.py
ftw/referencewidget/sources.py
ftw/referencewidget/testing.py
ftw/referencewidget/utils.py
ftw/referencewidget/widget.py
ftw/referencewidget/Extensions/install.py
ftw/referencewidget/browser/__init__.py
ftw/referencewidget/browser/configure.zcml
ftw/referencewidget/browser/utils.py
ftw/referencewidget/locales/ftw.referencewidget.pot
ftw/referencewidget/locales/de/LC_MESSAGES/ftw.referencewidget.po
ftw/referencewidget/profiles/default/metadata.xml
ftw/referencewidget/profiles/default/registry.xml
ftw/referencewidget/profiles/uninstall/registry.xml
ftw/referencewidget/resources/dist/referencewidget.es.js
ftw/referencewidget/resources/dist/referencewidget.umd.js
ftw/referencewidget/resources/src/main.js
ftw/referencewidget/resources/src/widget/App.vue
ftw/referencewidget/resources/src/widget/i18n.js
ftw/referencewidget/resources/src/widget/components/Breadcrumbs.vue
ftw/referencewidget/resources/src/widget/components/ListItems.vue
ftw/referencewidget/resources/src/widget/components/Pagination.vue
ftw/referencewidget/resources/src/widget/components/ResolveIcon.vue
ftw/referencewidget/resources/src/widget/components/searchForm.vue
ftw/referencewidget/templates/referencewidget_display.pt
ftw/referencewidget/templates/referencewidget_input.pt
ftw/referencewidget/tests/__init__.py
ftw/referencewidget/tests/builders.py
ftw/referencewidget/tests/test_change_widget_config.py
ftw/referencewidget/tests/test_converter.py
ftw/referencewidget/tests/test_datagrid_field.py
ftw/referencewidget/tests/test_override.py
ftw/referencewidget/tests/test_referencewidget_handler.py
ftw/referencewidget/tests/test_related_items_behavior.py
ftw_referencewidget-4.5.0.dist-info/METADATA
ftw_referencewidget-4.5.0.dist-info/WHEEL
ftw_referencewidget-4.5.0.dist-info/entry_points.txt
ftw_referencewidget-4.5.0.dist-info/top_level.txt
ftw_referencewidget-4.5.0.dist-info/RECORD
