Metadata-Version: 2.4
Name: ftw.referencewidget
Version: 4.5.0
Summary: A reference browser widget (Maintainer Mathias Leimgruber)
Home-page: https://github.com/webcloud7/ftw.referencewidget
Author: Mathias Leimgruber, webcloud7 ag
Author-email: mailto:info@webcloud7.ch
Maintainer: Mathias Leimgruber
License: GPL2
Keywords: webcloud7 widget reference browser
Classifier: Development Status :: 3 - Alpha
Classifier: Framework :: Plone
Classifier: Framework :: Plone :: 6.0
Classifier: Framework :: Plone :: 6.1
Classifier: Intended Audience :: Developers
Classifier: Programming Language :: Python
Classifier: Programming Language :: Python :: 3.11
Classifier: Programming Language :: Python :: 3.12
Requires-Dist: Plone
Requires-Dist: setuptools
Requires-Dist: plone.app.registry
Requires-Dist: z3c.relationfield
Requires-Dist: plone.z3cform
Requires-Dist: plone.app.z3cform
Requires-Dist: plone.app.intid
Requires-Dist: plone.app.relationfield
Requires-Dist: ftw.upgrade
Requires-Dist: plone.api
Requires-Dist: plone.restapi
Provides-Extra: tests
Requires-Dist: collective.z3cform.datagridfield; extra == "tests"
Requires-Dist: plone.app.testing; extra == "tests"
Requires-Dist: ftw.builder; extra == "tests"
Requires-Dist: ftw.testing; extra == "tests"
Requires-Dist: ftw.testbrowser; extra == "tests"
Provides-Extra: test
Requires-Dist: collective.z3cform.datagridfield; extra == "test"
Requires-Dist: plone.app.testing; extra == "test"
Requires-Dist: ftw.builder; extra == "test"
Requires-Dist: ftw.testing; extra == "test"
Requires-Dist: ftw.testbrowser; extra == "test"
Dynamic: author
Dynamic: author-email
Dynamic: classifier
Dynamic: description
Dynamic: home-page
Dynamic: keywords
Dynamic: license
Dynamic: maintainer
Dynamic: provides-extra
Dynamic: requires-dist
Dynamic: summary
